LICENSE
MANIFEST.in
README.rst
setup.py
storjtorrent/__init__.py
storjtorrent/exception.py
storjtorrent/session.py
storjtorrent/storjtorrent.py
storjtorrent/thread_management.py
storjtorrent/version.py
storjtorrent.egg-info/PKG-INFO
storjtorrent.egg-info/SOURCES.txt
storjtorrent.egg-info/dependency_links.txt
storjtorrent.egg-info/top_level.txt