Metadata-Version: 1.1
Name: storjtorrent
Version: 0.1.2
Summary: StorjTorrent is a wrapper library for libtorrent.
Home-page: https://github.com/Storj/storjtorrent
Author: Josh Brandoff
Author-email: josh@storj.io
License: The MIT License (MIT)
